{"lines":[[{"c":"9","line":{"pinyinSpaced":1},"v":1,"n":1,"p":""},{"c":"十二月","p":"Shí ’èr yuè"},{"c":"(","p":""},{"c":"就是","p":"jiù shì"},{"c":"亚达月","p":"Yà dá yuè"},{"c":")"},{"c":"十三日","p":"Shí sān rì"},{"c":","},{"c":"执行","p":"zhí xíng"},{"c":"王谕","p":"wáng yù"},{"c":"和","p":"hé"},{"c":"王法","p":"wáng fǎ"},{"c":"的","p":"de"},{"c":"日子","p":"rì zi"},{"c":"到了","p":"dào le"},{"c":"。"},{"c":"仇敌","p":"Chóu dí"},{"c":"本来","p":"běn lái"},{"c":"等着","p":"děng zhe"},{"c":"在","p":"zài"},{"c":"这","p":"zhè"},{"c":"天","p":"tiān"},{"c":"压制","p":"yā zhì"},{"c":"犹太人","p":"Yóu tài rén"},{"c":","},{"c":"怎","p":"zěn"},{"c":"料","p":"liào"},{"c":"犹太人","p":"Yóu tài rén"},{"c":"反过来","p":"fǎn guo lái"},{"c":"压制","p":"yā zhì"},{"c":"恨","p":"hèn"},{"c":"他们","p":"tā men"},{"c":"的","p":"de"},{"c":"人","p":"rén"},{"c":"。"},{"c":"2","v":2,"p":""},{"c":"犹太人","p":"Yóu tài rén"},{"c":"在","p":"zài"},{"c":"亚哈随鲁","p":"Yà hā suí lǔ"},{"c":"王","p":"wáng"},{"c":"治下","p":"zhì xià"},{"c":"各省","p":"gè shěng"},{"c":"的","p":"de"},{"c":"城","p":"chéng"},{"c":"里","p":"lǐ"},{"c":"聚集起来","p":"jù jí qi lai"},{"c":","},{"c":"要","p":"yào"},{"c":"下手","p":"xià shǒu"},{"c":"对付","p":"duì fu"},{"c":"那些","p":"nà xiē"},{"c":"想","p":"xiǎng"},{"c":"害","p":"hài"},{"c":"他们","p":"tā men"},{"c":"的","p":"de"},{"c":"人","p":"rén"},{"c":"。"},{"c":"没有","p":"Méi yǒu"},{"c":"人","p":"rén"},{"c":"能","p":"néng"},{"c":"在","p":"zài"},{"c":"他们","p":"tā men"},{"c":"面前","p":"miàn qián"},{"c":"站得稳","p":"zhàn de wěn"},{"c":","},{"c":"因为","p":"yīn wèi"},{"c":"各","p":"gè"},{"c":"族","p":"zú"},{"c":"都","p":"dōu"},{"c":"惧怕","p":"jù pà"},{"c":"犹太人","p":"Yóu tài rén"},{"c":"。"},{"c":"3","v":3,"p":""},{"c":"各省","p":"Gè shěng"},{"c":"君侯","p":"jūn hóu"},{"c":"、"},{"c":"总督","p":"zǒng dū"},{"c":"、"},{"c":"省长","p":"shěng zhǎng"},{"c":"和","p":"hé"},{"c":"办理","p":"bàn lǐ"},{"c":"王","p":"wáng"},{"c":"务","p":"wù"},{"c":"的","p":"de"},{"c":"人","p":"rén"},{"c":","},{"c":"都","p":"dōu"},{"c":"协助","p":"xié zhù"},{"c":"犹太人","p":"Yóu tài rén"},{"c":","},{"c":"因为","p":"yīn wèi"},{"c":"他们","p":"tā men"},{"c":"都","p":"dōu"},{"c":"惧怕","p":"jù pà"},{"c":"末底改","p":"Mò dǐ gǎi"},{"c":"。"},{"c":"4","v":4,"p":""},{"c":"末底改","p":"Mò dǐ gǎi"},{"c":"在","p":"zài"},{"c":"王宫","p":"wáng gōng"},{"c":"里","p":"lǐ"},{"c":"位高权重","p":"wèi gāo quán zhòng"},{"c":","},{"c":"他","p":"tā"},{"c":"的","p":"de"},{"c":"名声","p":"míng shēng"},{"c":"传遍","p":"chuán biàn"},{"c":"各省","p":"gè shěng"},{"c":"。"},{"c":"末底改","p":"Mò dǐ gǎi"},{"c":"这个","p":"zhè ge"},{"c":"人","p":"rén"},{"c":"就","p":"jiù"},{"c":"日益","p":"rì yì"},{"c":"尊大","p":"zūn dà"},{"c":"。"},{"c":"5","v":5,"n":1,"p":""},{"c":"犹太人","p":"Yóu tài rén"},{"c":"用","p":"yòng"},{"c":"剑","p":"jiàn"},{"c":"大大","p":"dà dà"},{"c":"击杀","p":"jī shā"},{"c":"他们","p":"tā men"},{"c":"的","p":"de"},{"c":"所有","p":"suǒ yǒu"},{"c":"仇敌","p":"chóu dí"},{"c":","},{"c":"把","p":"bǎ"},{"c":"他们","p":"tā men"},{"c":"消灭净尽","p":"xiāo miè jìng jìn"},{"c":","},{"c":"又","p":"yòu"},{"c":"随意","p":"suí yì"},{"c":"对付","p":"duì fu"},{"c":"那些","p":"nà xiē"},{"c":"恨","p":"hèn"},{"c":"他们","p":"tā men"},{"c":"的","p":"de"},{"c":"人","p":"rén"},{"c":"。"},{"c":"6","v":6,"p":""},{"c":"在","p":"Zài"},{"c":"书珊","p":"Shū shān"},{"c":"城堡","p":"chéng bǎo"},{"c":","},{"c":"犹太人","p":"Yóu tài rén"},{"c":"杀死","p":"shā sǐ"},{"c":"除灭了","p":"chú miè le"},{"c":"五百","p":"wǔ bǎi"},{"c":"人","p":"rén"},{"c":"。"},{"c":"7","v":7,"p":""},{"c":"巴珊达他","p":"Bā shān dá tā"},{"c":"、"},{"c":"达分","p":"Dá fēn"},{"c":"、"},{"c":"亚斯帕他","p":"Yà sī pà tā"},{"c":"、"},{"c":"8","v":8,"p":""},{"c":"波拉塔","p":"Bō lā tǎ"},{"c":"、"},{"c":"亚大利雅","p":"Yà dà lì yǎ"},{"c":"、"},{"c":"亚利大他","p":"Yà lì dà tā"},{"c":"、"},{"c":"9","v":9,"p":""},{"c":"帕玛斯他","p":"Pà mǎ sī tā"},{"c":"、"},{"c":"亚利赛","p":"Yà lì sài"},{"c":"、"},{"c":"亚利代","p":"Yà lì dài"},{"c":"、"},{"c":"瓦耶撒他","p":"Wǎ yē sā tā"},{"c":","},{"c":"10","v":10,"p":""},{"c":"这","p":"zhè"},{"c":"十个","p":"shí ge"},{"c":"人","p":"rén"},{"c":"是","p":"shì"},{"c":"哈米大他","p":"Hā mǐ dà tā"},{"c":"的","p":"de"},{"c":"孙子","p":"sūn zi"},{"c":"、"},{"c":"仇视","p":"chóu shì"},{"c":"犹太人","p":"Yóu tài rén"},{"c":"的","p":"de"},{"c":"哈曼","p":"Hā màn"},{"c":"的","p":"de"},{"c":"儿子","p":"ér zi"},{"c":"。"},{"c":"犹太人","p":"Yóu tài rén"},{"c":"杀了","p":"shā le"},{"c":"他们","p":"tā men"},{"c":","},{"c":"却","p":"què"},{"c":"没有","p":"méi yǒu"},{"c":"下手","p":"xià shǒu"},{"c":"夺取","p":"duó qǔ"},{"c":"财物","p":"cái wù"},{"c":"。"},{"c":"11","v":11,"n":1,"p":""},{"c":"当天","p":"Dàng tiān"},{"c":","},{"c":"书珊","p":"Shū shān"},{"c":"城堡","p":"chéng bǎo"},{"c":"被杀","p":"bèi shā"},{"c":"的","p":"de"},{"c":"人","p":"rén"},{"c":"的","p":"de"},{"c":"数目","p":"shù mù"},{"c":"给","p":"gěi"},{"c":"呈到","p":"chéng dào"},{"c":"王","p":"wáng"},{"c":"面前","p":"miàn qián"},{"c":"。"},{"c":"12","v":12,"n":1,"p":""},{"c":"王","p":"Wáng"},{"c":"对","p":"duì"},{"c":"王后","p":"wáng hòu"},{"c":"以斯帖","p":"Yǐ sī tiē"},{"c":"说","p":"shuō"},{"c":":"},{"c":"“","p":""},{"c":"犹太人","p":"Yóu tài rén"},{"c":"在","p":"zài"},{"c":"书珊","p":"Shū shān"},{"c":"城堡","p":"chéng bǎo"},{"c":"杀死","p":"shā sǐ"},{"c":"除灭了","p":"chú miè le"},{"c":"五百","p":"wǔ bǎi"},{"c":"人","p":"rén"},{"c":","},{"c":"还有","p":"hái yǒu"},{"c":"哈曼","p":"Hā màn"},{"c":"的","p":"de"},{"c":"十个","p":"shí ge"},{"c":"儿子","p":"ér zi"},{"c":"。"},{"c":"在","p":"Zài"},{"c":"本","p":"běn"},{"c":"王","p":"wáng"},{"c":"其余","p":"qí yú"},{"c":"的","p":"de"},{"c":"省份","p":"shěng fèn"},{"c":","},{"c":"他们","p":"tā men"},{"c":"又","p":"yòu"},{"c":"做","p":"zuò"},{"c":"得","p":"dé"},{"c":"怎么样","p":"zěn me yàng"},{"c":"呢","p":"ne"},{"c":"?"},{"c":"现在","p":"Xiàn zài"},{"c":"你","p":"nǐ"},{"c":"要","p":"yào"},{"c":"什么","p":"shén me"},{"c":"呢","p":"ne"},{"c":"?"},{"c":"我","p":"Wǒ"},{"c":"一定","p":"yí dìng"},{"c":"赐给","p":"cì gěi"},{"c":"你","p":"nǐ"},{"c":"。"},{"c":"你","p":"Nǐ"},{"c":"还","p":"hái"},{"c":"想","p":"xiǎng"},{"c":"求","p":"qiú"},{"c":"什么","p":"shén me"},{"c":"?"},{"c":"我","p":"Wǒ"},{"c":"也","p":"yě"},{"c":"必","p":"bì"},{"c":"成全","p":"chéng quán"},{"c":"你","p":"nǐ"},{"c":"。”"},{"c":"13","v":13,"p":""},{"c":"以斯帖","p":"Yǐ sī tiē"},{"c":"说","p":"shuō"},{"c":":"},{"c":"“","p":""},{"c":"如果","p":"Rú guǒ"},{"c":"我","p":"wǒ"},{"c":"王","p":"wáng"},{"c":"赞成","p":"zàn chéng"},{"c":","},{"c":"请","p":"qǐng"},{"c":"允准","p":"yǔn zhǔn"},{"c":"书珊","p":"Shū shān"},{"c":"的","p":"de"},{"c":"犹太人","p":"Yóu tài rén"},{"c":","},{"c":"明天","p":"míng tiān"},{"c":"再","p":"zài"},{"c":"照","p":"zhào"},{"c":"今天","p":"jīn tiān"},{"c":"的","p":"de"},{"c":"法令","p":"fǎ lìng"},{"c":"去","p":"qù"},{"c":"做","p":"zuò"},{"c":","},{"c":"并且","p":"bìng qiě"},{"c":"把","p":"bǎ"},{"c":"哈曼","p":"Hā màn"},{"c":"的","p":"de"},{"c":"十个","p":"shí ge"},{"c":"儿子","p":"ér zi"},{"c":"挂","p":"guà"},{"c":"在","p":"zài"},{"c":"木柱","p":"mù zhù"},{"c":"上","p":"shang"},{"c":"。”"},{"c":"14","v":14,"p":""},{"c":"王","p":"Wáng"},{"c":"就","p":"jiù"},{"c":"下令","p":"xià lìng"},{"c":"这样","p":"zhè yàng"},{"c":"做","p":"zuò"},{"c":"。"},{"c":"于是","p":"Yú shì"},{"c":"法令","p":"fǎ lìng"},{"c":"在","p":"zài"},{"c":"书珊","p":"Shū shān"},{"c":"颁布","p":"bān bù"},{"c":","},{"c":"人","p":"rén"},{"c":"也","p":"yě"},{"c":"把","p":"bǎ"},{"c":"哈曼","p":"Hā màn"},{"c":"的","p":"de"},{"c":"十个","p":"shí ge"},{"c":"儿子","p":"ér zi"},{"c":"挂了","p":"guà le"},{"c":"起来","p":"qǐ lai"},{"c":"。"},{"c":"15","v":15,"n":1,"p":""},{"c":"亚达月","p":"Yà dá yuè"},{"c":"十四","p":"shí sì"},{"c":"日","p":"rì"},{"c":","},{"c":"书珊","p":"Shū shān"},{"c":"的","p":"de"},{"c":"犹太人","p":"Yóu tài rén"},{"c":"又","p":"yòu"},{"c":"聚集起来","p":"jù jí qi lai"},{"c":","},{"c":"在","p":"zài"},{"c":"书珊","p":"Shū shān"},{"c":"杀了","p":"shā le"},{"c":"三百人","p":"sān bǎi rén"},{"c":","},{"c":"却","p":"què"},{"c":"没有","p":"méi yǒu"},{"c":"下手","p":"xià shǒu"},{"c":"夺取","p":"duó qǔ"},{"c":"财物","p":"cái wù"},{"c":"。"},{"c":"16","v":16,"n":1,"p":""},{"c":"在","p":"Zài"},{"c":"王","p":"wáng"},{"c":"各省","p":"gè shěng"},{"c":"其余","p":"qí yú"},{"c":"的","p":"de"},{"c":"犹太人","p":"Yóu tài rén"},{"c":"也","p":"yě"},{"c":"都","p":"dōu"},{"c":"聚集起来","p":"jù jí qi lai"},{"c":","},{"c":"奋起","p":"fèn qǐ"},{"c":"保护","p":"bǎo hù"},{"c":"性命","p":"xìng mìng"},{"c":","},{"c":"向","p":"xiàng"},{"c":"他们","p":"tā men"},{"c":"的","p":"de"},{"c":"敌人","p":"dí rén"},{"c":"报仇","p":"bào chóu"},{"c":","},{"c":"杀了","p":"shā le"},{"c":"恨","p":"hèn"},{"c":"他们","p":"tā men"},{"c":"的","p":"de"},{"c":"人","p":"rén"},{"c":"共","p":"gòng"},{"c":"七万","p":"qī wàn"},{"c":"五千","p":"wǔ qiān"},{"c":","},{"c":"却","p":"què"},{"c":"没有","p":"méi yǒu"},{"c":"下手","p":"xià shǒu"},{"c":"夺取","p":"duó qǔ"},{"c":"财物","p":"cái wù"},{"c":"。"},{"c":"17","v":17,"p":""},{"c":"这","p":"Zhè"},{"c":"是","p":"shì"},{"c":"亚达月","p":"Yà dá yuè"},{"c":"十三日","p":"shí sān rì"},{"c":"的","p":"de"},{"c":"事","p":"shì"},{"c":","},{"c":"他们","p":"tā men"},{"c":"在","p":"zài"},{"c":"十四","p":"shí sì"},{"c":"日","p":"rì"},{"c":"休息","p":"xiū xi"},{"c":","},{"c":"把","p":"bǎ"},{"c":"当天","p":"dàng tiān"},{"c":"定做","p":"dìng zuò"},{"c":"设宴","p":"shè yàn"},{"c":"欢庆","p":"huān qìng"},{"c":"的","p":"de"},{"c":"日子","p":"rì zi"},{"c":"。"},{"c":"18","v":18,"n":1,"p":""},{"c":"书珊","p":"Shū shān"},{"c":"的","p":"de"},{"c":"犹太人","p":"Yóu tài rén"},{"c":"却","p":"què"},{"c":"在","p":"zài"},{"c":"十三","p":"shí sān"},{"c":"、"},{"c":"十四","p":"shí sì"},{"c":"日","p":"rì"},{"c":"聚集","p":"jù jí"},{"c":","},{"c":"在","p":"zài"},{"c":"十五","p":"shí wǔ"},{"c":"日","p":"rì"},{"c":"休息","p":"xiū xi"},{"c":","},{"c":"把","p":"bǎ"},{"c":"当天","p":"dàng tiān"},{"c":"定做","p":"dìng zuò"},{"c":"设宴","p":"shè yàn"},{"c":"欢庆","p":"huān qìng"},{"c":"的","p":"de"},{"c":"日子","p":"rì zi"},{"c":"。"},{"c":"19","v":19,"p":""},{"c":"因此","p":"Yīn cǐ"},{"c":"住","p":"zhù"},{"c":"在","p":"zài"},{"c":"书珊","p":"Shū shān"},{"c":"外围","p":"wài wéi"},{"c":"城镇","p":"chéng zhèn"},{"c":"的","p":"de"},{"c":"犹太","p":"Yóu tài"},{"c":"乡民","p":"xiāng mín"},{"c":","},{"c":"都","p":"dōu"},{"c":"把","p":"bǎ"},{"c":"亚达月","p":"Yà dá yuè"},{"c":"十四","p":"shí sì"},{"c":"日","p":"rì"},{"c":"定做","p":"dìng zuò"},{"c":"佳","p":"jiā"},{"c":"日","p":"rì"},{"c":","},{"c":"设宴","p":"shè yàn"},{"c":"欢庆","p":"huān qìng"},{"c":","},{"c":"互","p":"hù"},{"c":"送","p":"sòng"},{"c":"食物","p":"shí wù"},{"c":"。"},{"c":"20","v":20,"n":1,"p":""},{"c":"末底改","p":"Mò dǐ gǎi"},{"c":"把","p":"bǎ"},{"c":"这些","p":"zhè xiē"},{"c":"事","p":"shì"},{"c":"写","p":"xiě"},{"c":"下来","p":"xià lai"},{"c":","},{"c":"发文","p":"fā wén"},{"c":"书","p":"shū"},{"c":"给","p":"gěi"},{"c":"亚哈随鲁","p":"Yà hā suí lǔ"},{"c":"王","p":"wáng"},{"c":"治下","p":"zhì xià"},{"c":"远近","p":"yuǎn jìn"},{"c":"各省","p":"gè shěng"},{"c":"的","p":"de"},{"c":"所有","p":"suǒ yǒu"},{"c":"犹太人","p":"Yóu tài rén"},{"c":","},{"c":"21","v":21,"p":""},{"c":"规定","p":"guī dìng"},{"c":"他们","p":"tā men"},{"c":"年年","p":"nián nián"},{"c":"都","p":"dōu"},{"c":"要","p":"yào"},{"c":"守","p":"shǒu"},{"c":"亚达月","p":"Yà dá yuè"},{"c":"十四","p":"shí sì"},{"c":"、"},{"c":"十五","p":"shí wǔ"},{"c":"日","p":"rì"},{"c":"。"},{"c":"22","v":22,"p":""},{"c":"在","p":"Zài"},{"c":"这两天","p":"zhè liǎng tiān"},{"c":","},{"c":"犹太人","p":"Yóu tài rén"},{"c":"摆脱","p":"bǎi tuō"},{"c":"仇敌","p":"chóu dí"},{"c":","},{"c":"得以","p":"dé yǐ"},{"c":"安歇","p":"ān xiē"},{"c":";"},{"c":"在","p":"zài"},{"c":"这个月","p":"zhèi gè yuè"},{"c":","},{"c":"他们","p":"tā men"},{"c":"化","p":"huà"},{"c":"悲","p":"bēi"},{"c":"为","p":"wèi"},{"c":"喜","p":"xǐ"},{"c":","},{"c":"转","p":"zhuǎn"},{"c":"哀","p":"āi"},{"c":"为乐","p":"wéi lè"},{"c":","},{"c":"得享","p":"dé xiǎng"},{"c":"佳","p":"jiā"},{"c":"日","p":"rì"},{"c":"。"},{"c":"所以","p":"Suǒ yǐ"},{"c":"他们","p":"tā men"},{"c":"要","p":"yào"},{"c":"在","p":"zài"},{"c":"这两天","p":"zhè liǎng tiān"},{"c":"设宴","p":"shè yàn"},{"c":"欢庆","p":"huān qìng"},{"c":","},{"c":"互","p":"hù"},{"c":"送","p":"sòng"},{"c":"食物","p":"shí wù"},{"c":","},{"c":"周济","p":"zhōu jì"},{"c":"穷人","p":"qióng rén"},{"c":"。"},{"c":"23","v":23,"n":1,"p":""},{"c":"犹太人","p":"Yóu tài rén"},{"c":"同意","p":"tóng yì"},{"c":"以后","p":"yǐ hòu"},{"c":"继续","p":"jì xù"},{"c":"这样","p":"zhè yàng"},{"c":"做","p":"zuò"},{"c":","},{"c":"又","p":"yòu"},{"c":"同意","p":"tóng yì"},{"c":"要","p":"yào"},{"c":"遵从","p":"zūn cóng"},{"c":"末底改","p":"Mò dǐ gǎi"},{"c":"写给","p":"xiě gěi"},{"c":"他们","p":"tā men"},{"c":"的","p":"de"},{"c":"话","p":"huà"},{"c":"。"},{"c":"24","v":24,"p":""},{"c":"亚甲人","p":"Yà jiǎ rén"},{"c":"哈米大他","p":"Hā mǐ dà tā"},{"c":"的","p":"de"},{"c":"儿子","p":"ér zi"},{"c":"哈曼","p":"Hā màn"},{"c":"仇视","p":"chóu shì"},{"c":"所有","p":"suǒ yǒu"},{"c":"犹太人","p":"Yóu tài rén"},{"c":","},{"c":"图谋","p":"tú móu"},{"c":"消灭","p":"xiāo miè"},{"c":"他们","p":"tā men"},{"c":","},{"c":"于是","p":"yú shì"},{"c":"抽","p":"chōu"},{"c":"“","p":""},{"c":"普珥","p":"Pǔ ’ěr"},{"c":"”,"},{"c":"就是","p":"jiù shì"},{"c":"抽签","p":"chōu qiān"},{"c":","},{"c":"要","p":"yào"},{"c":"犹太人","p":"Yóu tài rén"},{"c":"溃乱","p":"kuì luàn"},{"c":"灭亡","p":"miè wáng"},{"c":"。"},{"c":"25","v":25,"p":""},{"c":"可是","p":"Kě shì"},{"c":"以斯帖","p":"Yǐ sī tiē"},{"c":"谒见","p":"yè jiàn"},{"c":"国王","p":"guó wáng"},{"c":","},{"c":"王","p":"wáng"},{"c":"就","p":"jiù"},{"c":"下诏","p":"xià zhào"},{"c":"说","p":"shuō"},{"c":":"},{"c":"“","p":""},{"c":"哈曼","p":"Hā màn"},{"c":"谋害","p":"móu hài"},{"c":"犹太人","p":"Yóu tài rén"},{"c":","},{"c":"要","p":"yào"},{"c":"自食其果","p":"zì shí qí guǒ"},{"c":"。”"},{"c":"人","p":"Rén"},{"c":"就","p":"jiù"},{"c":"把","p":"bǎ"},{"c":"他","p":"tā"},{"c":"和","p":"hé"},{"c":"他","p":"tā"},{"c":"的","p":"de"},{"c":"儿子","p":"ér zi"},{"c":"挂","p":"guà"},{"c":"在","p":"zài"},{"c":"木柱","p":"mù zhù"},{"c":"上","p":"shang"},{"c":"。"},{"c":"26","v":26,"p":""},{"c":"因此","p":"Yīn cǐ"},{"c":","},{"c":"犹太人","p":"Yóu tài rén"},{"c":"依据","p":"yī jù"},{"c":"“","p":""},{"c":"普珥","p":"Pǔ ’ěr"},{"c":"”"},{"c":"这个","p":"zhè ge"},{"c":"名称","p":"míng chēng"},{"c":","},{"c":"把","p":"bǎ"},{"c":"这两天","p":"zhè liǎng tiān"},{"c":"叫做","p":"jiào zuò"},{"c":"“","p":""},{"c":"普珥节","p":"Pǔ ’ěr jié"},{"c":"”。"},{"c":"他们","p":"Tā men"},{"c":"因","p":"yīn"},{"c":"这","p":"zhè"},{"c":"文书","p":"wén shū"},{"c":"上","p":"shang"},{"c":"的","p":"de"},{"c":"一切","p":"yí qiè"},{"c":"话","p":"huà"},{"c":","},{"c":"又","p":"yòu"},{"c":"因","p":"yīn"},{"c":"所","p":"suǒ"},{"c":"看见","p":"kàn jiàn"},{"c":"所","p":"suǒ"},{"c":"遭遇","p":"zāo yù"},{"c":"的","p":"de"},{"c":"事","p":"shì"},{"c":","},{"c":"27","v":27,"p":""},{"c":"就","p":"jiù"},{"c":"做出","p":"zuò chū"},{"c":"规定","p":"guī dìng"},{"c":","},{"c":"同意","p":"tóng yì"},{"c":"要","p":"yào"},{"c":"自己","p":"zì jǐ"},{"c":"和","p":"hé"},{"c":"子孙","p":"zǐ sūn"},{"c":","},{"c":"以及","p":"yǐ jí"},{"c":"所有","p":"suǒ yǒu"},{"c":"归附","p":"guī fù"},{"c":"犹太人","p":"Yóu tài rén"},{"c":"的","p":"de"},{"c":"人","p":"rén"},{"c":","},{"c":"年年","p":"nián nián"},{"c":"照着","p":"zhào zhe"},{"c":"写给","p":"xiě gěi"},{"c":"他们","p":"tā men"},{"c":"的","p":"de"},{"c":"话","p":"huà"},{"c":","},{"c":"按","p":"àn"},{"c":"定期","p":"dìng qī"},{"c":"守","p":"shǒu"},{"c":"这两天","p":"zhè liǎng tiān"},{"c":","},{"c":"永不","p":"yǒng bú"},{"c":"废止","p":"fèi zhǐ"},{"c":"。"},{"c":"28","v":28,"p":""},{"c":"世世代代","p":"Shì shì –dài dài"},{"c":"、"},{"c":"家家户户","p":"jiā jiā –hù hù"},{"c":"、"},{"c":"各省","p":"gè shěng"},{"c":"各","p":"gè"},{"c":"城","p":"chéng"},{"c":"都","p":"dōu"},{"c":"要","p":"yào"},{"c":"记念","p":"jì niàn"},{"c":"、"},{"c":"谨守","p":"jǐn shǒu"},{"c":"这两天","p":"zhè liǎng tiān"},{"c":"。"},{"c":"犹太人","p":"Yóu tài rén"},{"c":"永不","p":"yǒng bù"},{"c":"可","p":"kě"},{"c":"废除","p":"fèi chú"},{"c":"这两天","p":"zhè liǎng tiān"},{"c":"的","p":"de"},{"c":"普珥节","p":"Pǔ ’ěr jié"},{"c":","},{"c":"他们","p":"tā men"},{"c":"的","p":"de"},{"c":"子孙","p":"zǐ sūn"},{"c":"也","p":"yě"},{"c":"永不","p":"yǒng bù"},{"c":"可","p":"kě"},{"c":"停止","p":"tíng zhǐ"},{"c":"守","p":"shǒu"},{"c":"这个","p":"zhè ge"},{"c":"纪念","p":"jì niàn"},{"c":"的","p":"de"},{"c":"节期","p":"jié qī"},{"c":"。"},{"c":"29","v":29,"n":1,"p":""},{"c":"亚比哈","p":"Yà bǐ hā"},{"c":"的","p":"de"},{"c":"女儿","p":"nǚ ’ér"},{"c":"以斯帖","p":"Yǐ sī tiē"},{"c":"王后","p":"wáng hòu"},{"c":"和","p":"hé"},{"c":"犹太人","p":"Yóu tài rén"},{"c":"末底改","p":"Mò dǐ gǎi"},{"c":"写了","p":"xiě le"},{"c":"第二","p":"dì –èr"},{"c":"封","p":"fēng"},{"c":"极","p":"jí"},{"c":"有","p":"yǒu"},{"c":"效力","p":"xiào lì"},{"c":"的","p":"de"},{"c":"信","p":"xìn"},{"c":","},{"c":"要","p":"yào"},{"c":"确立","p":"què lì"},{"c":"有关","p":"yǒu guān"},{"c":"普珥节","p":"Pǔ ’ěr jié"},{"c":"的","p":"de"},{"c":"规定","p":"guī dìng"},{"c":"。"},{"c":"30","v":30,"p":""},{"c":"末底改","p":"Mò dǐ gǎi"},{"c":"用","p":"yòng"},{"c":"和平","p":"hé píng"},{"c":"真诚","p":"zhēn chéng"},{"c":"的","p":"de"},{"c":"措辞","p":"cuò cí"},{"c":","},{"c":"发文","p":"fā wén"},{"c":"书","p":"shū"},{"c":"给","p":"gěi"},{"c":"亚哈随鲁","p":"Yà hā suí lǔ"},{"c":"治下","p":"zhì xià"},{"c":"境","p":"jìng"},{"c":"内","p":"nèi"},{"c":"一百","p":"yì bǎi"},{"c":"二十七","p":"èr shi qī"},{"c":"个","p":"ge"},{"c":"省","p":"shěng"},{"c":"的","p":"de"},{"c":"所有","p":"suǒ yǒu"},{"c":"犹太人","p":"Yóu tài rén"},{"c":","},{"c":"31","v":31,"p":""},{"c":"为要","p":"wèi yào"},{"c":"确立","p":"què lì"},{"c":"定期","p":"dìng qī"},{"c":"守","p":"shǒu"},{"c":"两天","p":"liǎng tiān"},{"c":"普珥节","p":"Pǔ ’ěr jié"},{"c":","},{"c":"就是","p":"jiù shì"},{"c":"谨守","p":"jǐn shǒu"},{"c":"犹太人","p":"Yóu tài rén"},{"c":"末底改","p":"Mò dǐ gǎi"},{"c":"和","p":"hé"},{"c":"王后","p":"wáng hòu"},{"c":"以斯帖","p":"Yǐ sī tiē"},{"c":"给","p":"gěi"},{"c":"他们","p":"tā men"},{"c":"的","p":"de"},{"c":"规定","p":"guī dìng"},{"c":","},{"c":"也","p":"yě"},{"c":"是","p":"shì"},{"c":"谨守","p":"jǐn shǒu"},{"c":"他们","p":"tā men"},{"c":"为","p":"wèi"},{"c":"自己","p":"zì jǐ"},{"c":"和","p":"hé"},{"c":"子孙","p":"zǐ sūn"},{"c":"所","p":"suǒ"},{"c":"立","p":"lì"},{"c":"的","p":"de"},{"c":"规定","p":"guī dìng"},{"c":","},{"c":"遵守","p":"zūn shǒu"},{"c":"禁食","p":"jìn shí"},{"c":"呼求","p":"hū qiú"},{"c":"的","p":"de"},{"c":"事宜","p":"shì yí"},{"c":"。"},{"c":"32","v":32,"p":""},{"c":"以斯帖","p":"Yǐ sī tiē"},{"c":"的","p":"de"},{"c":"话","p":"huà"},{"c":"确立了","p":"què lì le"},{"c":"以上","p":"yǐ shàng"},{"c":"有关","p":"yǒu guān"},{"c":"普珥节","p":"Pǔ ’ěr jié"},{"c":"的","p":"de"},{"c":"事项","p":"shì xiàng"},{"c":","},{"c":"并且","p":"bìng qiě"},{"c":"记","p":"jì"},{"c":"在","p":"zài"},{"c":"书","p":"shū"},{"c":"上","p":"shang"},{"c":"。"}]]}