{"lines":[[{"c":"1","line":{"pinyinSpaced":1},"v":1,"p":""},{"c":"尊貴","p":"Zūn guì"},{"c":"的","p":"de"},{"c":"提阿非羅","p":"Tí ’ā fēi luó"},{"c":"先生","p":"xiān sheng"},{"c":"："},{"c":"現在","p":"Xiàn zài"},{"c":"有","p":"yǒu"},{"c":"很","p":"hěn"},{"c":"多","p":"duō"},{"c":"人","p":"rén"},{"c":"着手","p":"zhuó shǒu"},{"c":"編著","p":"biān zhù"},{"c":"，"},{"c":"記述","p":"jì shù"},{"c":"我們","p":"wǒ men"},{"c":"當中","p":"dāng zhōng"},{"c":"確鑿不移","p":"què záo –bù yí"},{"c":"的","p":"de"},{"c":"事","p":"shì"},{"c":"，"},{"c":"2","v":2,"p":""},{"c":"就是","p":"jiù shì"},{"c":"目擊","p":"mù jī"},{"c":"事情","p":"shì qing"},{"c":"始末","p":"shǐ mò"},{"c":"的","p":"de"},{"c":"傳道人","p":"chuán dào rén"},{"c":"傳給","p":"chuán gěi"},{"c":"我們","p":"wǒ men"},{"c":"的","p":"de"},{"c":"。"},{"c":"3","v":3,"p":""},{"c":"我","p":"Wǒ"},{"c":"既","p":"jì"},{"c":"從","p":"cóng"},{"c":"頭","p":"tóu"},{"c":"確切","p":"què qiè"},{"c":"地","p":"de"},{"c":"考證了","p":"kǎo zhèng le"},{"c":"一切","p":"yí qiè"},{"c":"，"},{"c":"也","p":"yě"},{"c":"就","p":"jiù"},{"c":"決心","p":"jué xīn"},{"c":"順着","p":"shùn zhe"},{"c":"次序","p":"cì xù"},{"c":"寫給","p":"xiě gěi"},{"c":"你","p":"nǐ"},{"c":"，"},{"c":"4","v":4,"p":""},{"c":"好叫","p":"hǎo jiào"},{"c":"你","p":"nǐ"},{"c":"清楚","p":"qīng chu"},{"c":"知道","p":"zhī dao"},{"c":"，"},{"c":"從前","p":"cóng qián"},{"c":"口頭","p":"kǒu tóu"},{"c":"上","p":"shang"},{"c":"教導","p":"jiào dǎo"},{"c":"你","p":"nǐ"},{"c":"的","p":"de"},{"c":"事","p":"shì"},{"c":"，"},{"c":"都","p":"dōu"},{"c":"是","p":"shì"},{"c":"真實","p":"zhēn shí"},{"c":"的","p":"de"},{"c":"。"}],[{"c":"5","v":5,"p":""},{"c":"猶地亞","p":"Yóu dì yà"},{"c":"王","p":"wáng"},{"c":"希律","p":"Xī lǜ"},{"c":"的","p":"de"},{"c":"日子","p":"rì zi"},{"c":"，"},{"c":"亞比雅","p":"Yà bǐ yǎ"},{"c":"班","p":"bān"},{"c":"裏","p":"lǐ"},{"c":"有","p":"yǒu"},{"c":"一","p":"yí"},{"c":"個","p":"ge"},{"c":"祭司","p":"jì sī"},{"c":"，"},{"c":"名","p":"míng"},{"c":"叫","p":"jiào"},{"c":"撒迦利亞","p":"Sā jiā lì yà"},{"c":"，"},{"c":"妻子","p":"qī zi"},{"c":"是","p":"shì"},{"c":"亞倫","p":"Yà lún"},{"c":"的","p":"de"},{"c":"後人","p":"hòu rén"},{"c":"，"},{"c":"名","p":"míng"},{"c":"叫","p":"jiào"},{"c":"伊利莎白","p":"Yī lì shā bái"},{"c":"。"},{"c":"6","v":6,"p":""},{"c":"他們","p":"Tā men"},{"c":"倆","p":"liǎ"},{"c":"在","p":"zài"},{"c":"上帝","p":"Shàng dì"},{"c":"面前","p":"miàn qián"},{"c":"都","p":"dōu"},{"c":"是","p":"shì"},{"c":"義人","p":"yì rén"},{"c":"，"},{"c":"遵行","p":"zūn xíng"},{"c":"耶和華","p":"Yē hé huá"},{"c":"的","p":"de"},{"c":"一切","p":"yí qiè"},{"c":"誡命","p":"jiè mìng"},{"c":"律例","p":"lǜ lì"},{"c":"，"},{"c":"無可","p":"wú kě"},{"c":"指責","p":"zhǐ zé"},{"c":"。"},{"c":"7","v":7,"p":""},{"c":"只","p":"Zhǐ"},{"c":"因","p":"yīn"},{"c":"伊利莎白","p":"Yī lì shā bái"},{"c":"不育","p":"bú yù"},{"c":"，"},{"c":"兩","p":"liǎng"},{"c":"人","p":"rén"},{"c":"也","p":"yě"},{"c":"上了","p":"shang le"},{"c":"年紀","p":"nián jì"},{"c":"，"},{"c":"就","p":"jiù"},{"c":"無兒","p":"wú ’ér"},{"c":"無女","p":"wú nǚ"},{"c":"。"}],[{"c":"8","v":8,"p":""},{"c":"有","p":"Yǒu"},{"c":"一","p":"yí"},{"c":"次","p":"cì"},{"c":"，"},{"c":"撒迦利亞","p":"Sā jiā lì yà"},{"c":"值班","p":"zhí bān"},{"c":"，"},{"c":"在","p":"zài"},{"c":"上帝","p":"Shàng dì"},{"c":"面前","p":"miàn qián"},{"c":"當","p":"dāng"},{"c":"祭司","p":"jì sī"},{"c":"，"},{"c":"9","v":9,"p":""},{"c":"照","p":"zhào"},{"c":"祭司","p":"jì sī"},{"c":"供職","p":"gòng zhí"},{"c":"的","p":"de"},{"c":"規矩","p":"guī ju"},{"c":"，"},{"c":"輪到","p":"lún dào"},{"c":"他","p":"tā"},{"c":"進","p":"jìn"},{"c":"耶和華","p":"Yē hé huá"},{"c":"的","p":"de"},{"c":"聖所","p":"Shèng suǒ"},{"c":"裏","p":"lǐ"},{"c":"獻","p":"xiàn"},{"c":"香","p":"xiāng"},{"c":"。"},{"c":"10","v":10,"p":""},{"c":"獻","p":"Xiàn"},{"c":"香","p":"xiāng"},{"c":"的","p":"de"},{"c":"時候","p":"shí hou"},{"c":"，"},{"c":"民眾","p":"mín zhòng"},{"c":"都","p":"dōu"},{"c":"在","p":"zài"},{"c":"外面","p":"wài miàn"},{"c":"禱告","p":"dǎo gào"},{"c":"。"},{"c":"11","v":11,"p":""},{"c":"耶和華","p":"Yē hé huá"},{"c":"的","p":"de"},{"c":"天使","p":"tiān shǐ"},{"c":"向","p":"xiàng"},{"c":"他","p":"tā"},{"c":"顯現","p":"xiǎn xiàn"},{"c":"，"},{"c":"站","p":"zhàn"},{"c":"在","p":"zài"},{"c":"香壇","p":"xiāng tán"},{"c":"右邊","p":"yòu bian"},{"c":"。"},{"c":"12","v":12,"p":""},{"c":"撒迦利亞","p":"Sā jiā lì yà"},{"c":"看見","p":"kàn jiàn"},{"c":"，"},{"c":"就","p":"jiù"},{"c":"惶恐不安","p":"huáng kǒng –bù ’ān"},{"c":"。"},{"c":"13","v":13,"p":""},{"c":"天使","p":"Tiān shǐ"},{"c":"對","p":"duì"},{"c":"他","p":"tā"},{"c":"説","p":"shuō"},{"c":"："},{"c":"“","p":""},{"c":"撒迦利亞","p":"Sā jiā lì yà"},{"c":"，"},{"c":"不要","p":"bú yào"},{"c":"怕","p":"pà"},{"c":"，"},{"c":"你","p":"nǐ"},{"c":"的","p":"de"},{"c":"懇切","p":"kěn qiè"},{"c":"祈求","p":"qí qiú"},{"c":"已經","p":"yǐ jing"},{"c":"得","p":"dé"},{"c":"蒙","p":"méng"},{"c":"垂聽","p":"chuí tīng"},{"c":"。"},{"c":"你","p":"Nǐ"},{"c":"妻子","p":"qī zi"},{"c":"伊利莎白","p":"Yī lì shā bái"},{"c":"必","p":"bì"},{"c":"給","p":"gěi"},{"c":"你生","p":"nǐ shēng"},{"c":"一","p":"yí"},{"c":"個","p":"ge"},{"c":"兒子","p":"ér zi"},{"c":"，"},{"c":"你","p":"nǐ"},{"c":"要","p":"yào"},{"c":"給","p":"gěi"},{"c":"他","p":"tā"},{"c":"起名","p":"qǐ míng"},{"c":"叫","p":"jiào"},{"c":"約翰","p":"Yuē hàn"},{"c":"。"},{"c":"14","v":14,"p":""},{"c":"你","p":"Nǐ"},{"c":"必","p":"bì"},{"c":"歡喜","p":"huān xǐ"},{"c":"快樂","p":"kuài lè"},{"c":"，"},{"c":"許多","p":"xǔ duō"},{"c":"人","p":"rén"},{"c":"也","p":"yě"},{"c":"必","p":"bì"},{"c":"因","p":"yīn"},{"c":"他","p":"tā"},{"c":"的","p":"de"},{"c":"出生","p":"chū shēng"},{"c":"而","p":"ér"},{"c":"喜樂","p":"xǐ lè"},{"c":"。"},{"c":"15","v":15,"p":""},{"c":"他","p":"Tā"},{"c":"在","p":"zài"},{"c":"耶和華","p":"Yē hé huá"},{"c":"面前","p":"miàn qián"},{"c":"必","p":"bì"},{"c":"尊","p":"zūn"},{"c":"為","p":"wèi"},{"c":"大","p":"dà"},{"c":"，"},{"c":"淡酒","p":"dàn jiǔ"},{"c":"烈酒","p":"liè jiǔ"},{"c":"都","p":"dōu"},{"c":"不","p":"bù"},{"c":"喝","p":"hē"},{"c":"，"},{"c":"在","p":"zài"},{"c":"母","p":"mǔ"},{"c":"腹","p":"fù"},{"c":"中","p":"zhōng"},{"c":"就","p":"jiù"},{"c":"充滿","p":"chōng mǎn"},{"c":"聖靈","p":"shèng líng"},{"c":"。"},{"c":"16","v":16,"p":""},{"c":"他","p":"Tā"},{"c":"必","p":"bì"},{"c":"使","p":"shǐ"},{"c":"許多","p":"xǔ duō"},{"c":"以色列人","p":"Yǐ sè liè rén"},{"c":"回頭","p":"huí tóu"},{"c":"，"},{"c":"歸附","p":"guī fù"},{"c":"他們","p":"tā men"},{"c":"的","p":"de"},{"c":"上帝","p":"Shàng dì"},{"c":"耶和華","p":"Yē hé huá"},{"c":"。"},{"c":"17","v":17,"p":""},{"c":"他","p":"Tā"},{"c":"必","p":"bì"},{"c":"有","p":"yǒu"},{"c":"以利亞","p":"Yǐ lì yà"},{"c":"的","p":"de"},{"c":"氣魄","p":"qì pò"},{"c":"和","p":"hé"},{"c":"能力","p":"néng lì"},{"c":"，"},{"c":"走在","p":"zǒu zài"},{"c":"上帝","p":"Shàng dì"},{"c":"前面","p":"qián mian"},{"c":"，"},{"c":"使","p":"shǐ"},{"c":"父親","p":"fù qin"},{"c":"回心轉意","p":"huí xīn –zhuǎn yì"},{"c":"，"},{"c":"接納","p":"jiē nà"},{"c":"兒女","p":"ér nǚ"},{"c":"；"},{"c":"使","p":"shǐ"},{"c":"悖逆","p":"bèi nì"},{"c":"的","p":"de"},{"c":"人","p":"rén"},{"c":"回頭","p":"huí tóu"},{"c":"，"},{"c":"接納","p":"jiē nà"},{"c":"義人","p":"yì rén"},{"c":"實用","p":"shí yòng"},{"c":"的","p":"de"},{"c":"智慧","p":"zhì huì"},{"c":"。"},{"c":"他","p":"Tā"},{"c":"要","p":"yào"},{"c":"為","p":"wèi"},{"c":"耶和華","p":"Yē hé huá"},{"c":"召集","p":"zhào jí"},{"c":"一","p":"yì"},{"c":"群","p":"qún"},{"c":"作妥","p":"zuò tuǒ"},{"c":"準備","p":"zhǔn bèi"},{"c":"的","p":"de"},{"c":"人","p":"rén"},{"c":"。”"}],[{"c":"18","v":18,"p":""},{"c":"撒迦利亞","p":"Sā jiā lì yà"},{"c":"對","p":"duì"},{"c":"天使","p":"tiān shǐ"},{"c":"説","p":"shuō"},{"c":"："},{"c":"“","p":""},{"c":"我","p":"Wǒ"},{"c":"怎能","p":"zěn néng"},{"c":"相信","p":"xiāng xìn"},{"c":"這","p":"zhè"},{"c":"件","p":"jiàn"},{"c":"事","p":"shì"},{"c":"呢","p":"ne"},{"c":"？"},{"c":"我","p":"Wǒ"},{"c":"老了","p":"lǎo le"},{"c":"，"},{"c":"我","p":"wǒ"},{"c":"的","p":"de"},{"c":"妻子","p":"qī zi"},{"c":"也","p":"yě"},{"c":"上了","p":"shang le"},{"c":"年紀","p":"nián jì"},{"c":"。”"},{"c":"19","v":19,"p":""},{"c":"天使","p":"Tiān shǐ"},{"c":"回答","p":"huí dá"},{"c":"説","p":"shuō"},{"c":"："},{"c":"“","p":""},{"c":"我","p":"Wǒ"},{"c":"是","p":"shì"},{"c":"侍立","p":"shì lì"},{"c":"在","p":"zài"},{"c":"上帝","p":"Shàng dì"},{"c":"面前","p":"miàn qián"},{"c":"的","p":"de"},{"c":"加百列","p":"Jiā bǎi liè"},{"c":"。"},{"c":"我","p":"Wǒ"},{"c":"奉差","p":"fèng chāi"},{"c":"對","p":"duì"},{"c":"你","p":"nǐ"},{"c":"説話","p":"shuō huà"},{"c":"，"},{"c":"把","p":"bǎ"},{"c":"這些","p":"zhè xiē"},{"c":"好","p":"hǎo"},{"c":"消息","p":"xiāo xi"},{"c":"告訴","p":"gào su"},{"c":"你","p":"nǐ"},{"c":"，"},{"c":"20","v":20,"p":""},{"c":"你","p":"nǐ"},{"c":"卻","p":"què"},{"c":"不","p":"bú"},{"c":"信","p":"xìn"},{"c":"我","p":"wǒ"},{"c":"的","p":"de"},{"c":"話","p":"huà"},{"c":"。"},{"c":"看","p":"Kàn"},{"c":"哪","p":"na"},{"c":"！"},{"c":"你","p":"Nǐ"},{"c":"必","p":"bì"},{"c":"成為","p":"chéng wéi"},{"c":"啞巴","p":"yǎ ba"},{"c":"，"},{"c":"不","p":"bù"},{"c":"能","p":"néng"},{"c":"説話","p":"shuō huà"},{"c":"，"},{"c":"直到","p":"zhí dào"},{"c":"這","p":"zhè"},{"c":"一切","p":"yí qiè"},{"c":"成就","p":"chéng jiù"},{"c":"的","p":"de"},{"c":"日子","p":"rì zi"},{"c":"。"},{"c":"我","p":"Wǒ"},{"c":"的","p":"de"},{"c":"話","p":"huà"},{"c":"到","p":"dào"},{"c":"指定","p":"zhǐ dìng"},{"c":"的","p":"de"},{"c":"時候","p":"shí hou"},{"c":"就","p":"jiù"},{"c":"必","p":"bì"},{"c":"應驗","p":"yìng yàn"},{"c":"。”"},{"c":"21","v":21,"p":""},{"c":"民眾","p":"Mín zhòng"},{"c":"在","p":"zài"},{"c":"等候","p":"děng hòu"},{"c":"撒迦利亞","p":"Sā jiā lì yà"},{"c":"，"},{"c":"見","p":"jiàn"},{"c":"他","p":"tā"},{"c":"在","p":"zài"},{"c":"聖所","p":"Shèng suǒ"},{"c":"裏","p":"lǐ"},{"c":"遲遲","p":"chí chí"},{"c":"不","p":"bù"},{"c":"出來","p":"chū lái"},{"c":"，"},{"c":"就","p":"jiù"},{"c":"覺得","p":"jué de"},{"c":"奇怪","p":"qí guài"},{"c":"。"},{"c":"22","v":22,"p":""},{"c":"等到","p":"Děng dào"},{"c":"他","p":"tā"},{"c":"出來","p":"chū lái"},{"c":"了","p":"le"},{"c":"，"},{"c":"他","p":"tā"},{"c":"卻","p":"què"},{"c":"不","p":"bù"},{"c":"能","p":"néng"},{"c":"説話","p":"shuō huà"},{"c":"，"},{"c":"大家","p":"dà jiā"},{"c":"才","p":"cái"},{"c":"知道","p":"zhī dao"},{"c":"他","p":"tā"},{"c":"在","p":"zài"},{"c":"聖所","p":"Shèng suǒ"},{"c":"裏","p":"lǐ"},{"c":"看見了","p":"kàn jiàn le"},{"c":"異象","p":"yì xiàng"},{"c":"。"},{"c":"他","p":"Tā"},{"c":"不斷","p":"bú duàn"},{"c":"打着","p":"dǎ zhe"},{"c":"手勢","p":"shǒu shì"},{"c":"，"},{"c":"始終","p":"shǐ zhōng"},{"c":"説不出","p":"shuō bù chū"},{"c":"話","p":"huà"},{"c":"來","p":"lái"},{"c":"。"},{"c":"23","v":23,"p":""},{"c":"履行","p":"Lǚ xíng"},{"c":"公職","p":"gōng zhí"},{"c":"的","p":"de"},{"c":"日子","p":"rì zi"},{"c":"滿","p":"mǎn"},{"c":"了","p":"le"},{"c":"，"},{"c":"他","p":"tā"},{"c":"就","p":"jiù"},{"c":"回家","p":"huí jiā"},{"c":"去","p":"qù"},{"c":"。"}],[{"c":"24","v":24,"p":""},{"c":"過了","p":"Guò le"},{"c":"一","p":"yí"},{"c":"段","p":"duàn"},{"c":"日子","p":"rì zi"},{"c":"，"},{"c":"他","p":"tā"},{"c":"妻子","p":"qī zi"},{"c":"伊利莎白","p":"Yī lì shā bái"},{"c":"懷了","p":"huái le"},{"c":"孕","p":"yùn"},{"c":"，"},{"c":"就","p":"jiù"},{"c":"沒有","p":"méi yǒu"},{"c":"露面","p":"lòu miàn"},{"c":"五","p":"wǔ"},{"c":"個","p":"ge"},{"c":"月","p":"yuè"},{"c":"。"},{"c":"她","p":"Tā"},{"c":"説","p":"shuō"},{"c":"："},{"c":"25","v":25,"p":""},{"c":"“","p":""},{"c":"耶和華","p":"Yē hé huá"},{"c":"眷顧","p":"juàn gù"},{"c":"我","p":"wǒ"},{"c":"，"},{"c":"在","p":"zài"},{"c":"這","p":"zhè"},{"c":"段","p":"duàn"},{"c":"日子","p":"rì zi"},{"c":"這樣","p":"zhè yàng"},{"c":"恩待","p":"ēn dài"},{"c":"我","p":"wǒ"},{"c":"，"},{"c":"把","p":"bǎ"},{"c":"我","p":"wǒ"},{"c":"在","p":"zài"},{"c":"眾人","p":"zhòng rén"},{"c":"面前","p":"miàn qián"},{"c":"的","p":"de"},{"c":"恥辱","p":"chǐ rǔ"},{"c":"除去","p":"chú qù"},{"c":"了","p":"le"},{"c":"。”"}],[{"c":"26","v":26,"p":""},{"c":"她","p":"Tā"},{"c":"懷孕","p":"huái yùn"},{"c":"的","p":"de"},{"c":"第六","p":"dì –liù"},{"c":"個","p":"ge"},{"c":"月","p":"yuè"},{"c":"，"},{"c":"天使","p":"tiān shǐ"},{"c":"加百列","p":"Jiā bǎi liè"},{"c":"奉","p":"fèng"},{"c":"上帝","p":"Shàng dì"},{"c":"差","p":"chāi"},{"c":"遣","p":"qiǎn"},{"c":"，"},{"c":"到","p":"dào"},{"c":"加利利","p":"Jiā lì lì"},{"c":"一","p":"yí"},{"c":"座","p":"zuò"},{"c":"名","p":"míng"},{"c":"叫","p":"jiào"},{"c":"拿撒勒","p":"Ná sā lè"},{"c":"的","p":"de"},{"c":"城","p":"chéng"},{"c":"去","p":"qù"},{"c":"，"},{"c":"27","v":27,"p":""},{"c":"要","p":"yào"},{"c":"見","p":"jiàn"},{"c":"一","p":"yí"},{"c":"個","p":"ge"},{"c":"處女","p":"chǔ nǚ"},{"c":"。"},{"c":"處女","p":"Chǔ nǚ"},{"c":"名","p":"míng"},{"c":"叫","p":"jiào"},{"c":"馬利亞","p":"Mǎ lì yà"},{"c":"，"},{"c":"已經","p":"yǐ jing"},{"c":"許配","p":"xǔ pèi"},{"c":"給","p":"gěi"},{"c":"大衛家","p":"Dà wèi jiā"},{"c":"一","p":"yí"},{"c":"個","p":"ge"},{"c":"名","p":"míng"},{"c":"叫","p":"jiào"},{"c":"約瑟","p":"Yuē sè"},{"c":"的","p":"de"},{"c":"人","p":"rén"},{"c":"。"},{"c":"28","v":28,"p":""},{"c":"天使","p":"Tiān shǐ"},{"c":"進去","p":"jìn qù"},{"c":"，"},{"c":"在","p":"zài"},{"c":"她","p":"tā"},{"c":"面前","p":"miàn qián"},{"c":"説","p":"shuō"},{"c":"："},{"c":"“","p":""},{"c":"蒙","p":"Méng"},{"c":"大恩","p":"dà ’ēn"},{"c":"的","p":"de"},{"c":"人","p":"rén"},{"c":"，"},{"c":"你","p":"nǐ"},{"c":"好","p":"hǎo"},{"c":"！"},{"c":"耶和華","p":"Yē hé huá"},{"c":"與","p":"yǔ"},{"c":"你","p":"nǐ"},{"c":"同在","p":"tóng zài"},{"c":"了","p":"le"},{"c":"。”"},{"c":"29","v":29,"p":""},{"c":"馬利亞","p":"Mǎ lì yà"},{"c":"一","p":"yì"},{"c":"聽見","p":"tīng jiàn"},{"c":"這","p":"zhè"},{"c":"句","p":"jù"},{"c":"話","p":"huà"},{"c":"就","p":"jiù"},{"c":"非常","p":"fēi cháng"},{"c":"不安","p":"bù ’ān"},{"c":"，"},{"c":"思量","p":"sī liang"},{"c":"這樣","p":"zhè yàng"},{"c":"的","p":"de"},{"c":"問候","p":"wèn hòu"},{"c":"究竟","p":"jiū jìng"},{"c":"是","p":"shì"},{"c":"甚麼","p":"shén me"},{"c":"意思","p":"yì si"},{"c":"。"},{"c":"30","v":30,"p":""},{"c":"天使","p":"Tiān shǐ"},{"c":"對","p":"duì"},{"c":"她","p":"tā"},{"c":"説","p":"shuō"},{"c":"："},{"c":"“","p":""},{"c":"馬利亞","p":"Mǎ lì yà"},{"c":"，"},{"c":"不要","p":"bú yào"},{"c":"怕","p":"pà"},{"c":"，"},{"c":"你","p":"nǐ"},{"c":"蒙","p":"méng"},{"c":"上帝","p":"Shàng dì"},{"c":"眷顧","p":"juàn gù"},{"c":"了","p":"le"},{"c":"。"},{"c":"31","v":31,"p":""},{"c":"你","p":"Nǐ"},{"c":"必","p":"bì"},{"c":"懷孕","p":"huái yùn"},{"c":"生子","p":"shēng zǐ"},{"c":"。"},{"c":"你","p":"Nǐ"},{"c":"要","p":"yào"},{"c":"給","p":"gěi"},{"c":"他","p":"tā"},{"c":"起名","p":"qǐ míng"},{"c":"叫","p":"jiào"},{"c":"耶穌","p":"Yē sū"},{"c":"。"},{"c":"32","v":32,"p":""},{"c":"他","p":"Tā"},{"c":"必","p":"bì"},{"c":"成為","p":"chéng wéi"},{"c":"偉大","p":"wěi dà"},{"c":"的","p":"de"},{"c":"人物","p":"rén wù"},{"c":"，"},{"c":"稱","p":"chēng"},{"c":"為","p":"wéi"},{"c":"至高者","p":"zhì gāo zhě"},{"c":"的","p":"de"},{"c":"兒子","p":"ér zi"},{"c":"。"},{"c":"耶和華","p":"Yē hé huá"},{"c":"上帝","p":"Shàng dì"},{"c":"必","p":"bì"},{"c":"把","p":"bǎ"},{"c":"他","p":"tā"},{"c":"祖先","p":"zǔ xiān"},{"c":"大衛","p":"Dà wèi"},{"c":"的","p":"de"},{"c":"寶座","p":"bǎo zuò"},{"c":"賜給","p":"cì gěi"},{"c":"他","p":"tā"},{"c":"，"},{"c":"33","v":33,"p":""},{"c":"他","p":"tā"},{"c":"必","p":"bì"},{"c":"作王","p":"zuò wáng"},{"c":"統治","p":"tǒng zhì"},{"c":"雅各家","p":"Yǎ gè jiā"},{"c":"，"},{"c":"永無窮盡","p":"yǒng wú qióng jìn"},{"c":"；"},{"c":"他","p":"tā"},{"c":"的","p":"de"},{"c":"王國","p":"wáng guó"},{"c":"必","p":"bì"},{"c":"沒有","p":"méi yǒu"},{"c":"終結","p":"zhōng jié"},{"c":"。”"}],[{"c":"34","v":34,"p":""},{"c":"馬利亞","p":"Mǎ lì yà"},{"c":"對","p":"duì"},{"c":"天使","p":"tiān shǐ"},{"c":"説","p":"shuō"},{"c":"："},{"c":"“","p":""},{"c":"我","p":"Wǒ"},{"c":"從","p":"cóng"},{"c":"沒有","p":"méi yǒu"},{"c":"與","p":"yǔ"},{"c":"男人","p":"nán rén"},{"c":"同寢","p":"tóng qǐn"},{"c":"，"},{"c":"這","p":"zhè"},{"c":"件","p":"jiàn"},{"c":"事","p":"shì"},{"c":"怎麼","p":"zěn me"},{"c":"發生","p":"fā shēng"},{"c":"呢","p":"ne"},{"c":"？”"},{"c":"35","v":35,"p":""},{"c":"天使","p":"Tiān shǐ"},{"c":"回答","p":"huí dá"},{"c":"説","p":"shuō"},{"c":"："},{"c":"“","p":""},{"c":"聖靈","p":"Shèng líng"},{"c":"必","p":"bì"},{"c":"臨到","p":"lín dào"},{"c":"你","p":"nǐ"},{"c":"身上","p":"shēn shang"},{"c":"，"},{"c":"至高者","p":"zhì gāo zhě"},{"c":"的","p":"de"},{"c":"力量","p":"lì liang"},{"c":"必","p":"bì"},{"c":"蔭庇","p":"yìn bì"},{"c":"你","p":"nǐ"},{"c":"，"},{"c":"因此","p":"yīn cǐ"},{"c":"你","p":"nǐ"},{"c":"將要","p":"jiāng yào"},{"c":"生","p":"shēng"},{"c":"的","p":"de"},{"c":"，"},{"c":"必","p":"bì"},{"c":"稱","p":"chēng"},{"c":"為","p":"wéi"},{"c":"聖者","p":"shèng zhě"},{"c":"，"},{"c":"稱","p":"chēng"},{"c":"為","p":"wéi"},{"c":"上帝","p":"Shàng dì"},{"c":"的","p":"de"},{"c":"兒子","p":"ér zi"},{"c":"。"},{"c":"36","v":36,"p":""},{"c":"看","p":"Kàn"},{"c":"，"},{"c":"你","p":"nǐ"},{"c":"親戚","p":"qīn qi"},{"c":"伊利莎白","p":"Yī lì shā bái"},{"c":"素","p":"sù"},{"c":"被","p":"bèi"},{"c":"稱","p":"chēng"},{"c":"為","p":"wéi"},{"c":"不育","p":"bú yù"},{"c":"的","p":"de"},{"c":"婦人","p":"fù rén"},{"c":"，"},{"c":"雖然","p":"suī rán"},{"c":"年老","p":"nián lǎo"},{"c":"，"},{"c":"卻","p":"què"},{"c":"也","p":"yě"},{"c":"懷了","p":"huái le"},{"c":"男","p":"nán"},{"c":"胎","p":"tāi"},{"c":"，"},{"c":"現在","p":"xiàn zài"},{"c":"到","p":"dào"},{"c":"第六","p":"dì –liù"},{"c":"個","p":"ge"},{"c":"月","p":"yuè"},{"c":"了","p":"le"},{"c":"。"},{"c":"37","v":37,"p":""},{"c":"上帝","p":"Shàng dì"},{"c":"所","p":"suǒ"},{"c":"説","p":"shuō"},{"c":"的","p":"de"},{"c":"事","p":"shì"},{"c":"，"},{"c":"沒有","p":"méi yǒu"},{"c":"不","p":"bù"},{"c":"能","p":"néng"},{"c":"實現","p":"shí xiàn"},{"c":"的","p":"de"},{"c":"。”"},{"c":"38","v":38,"p":""},{"c":"馬利亞","p":"Mǎ lì yà"},{"c":"説","p":"shuō"},{"c":"："},{"c":"“","p":""},{"c":"看","p":"Kàn"},{"c":"哪","p":"na"},{"c":"！"},{"c":"我","p":"Wǒ"},{"c":"是","p":"shì"},{"c":"耶和華","p":"Yē hé huá"},{"c":"的","p":"de"},{"c":"婢女","p":"bì nǚ"},{"c":"！"},{"c":"願","p":"Yuàn"},{"c":"你","p":"nǐ"},{"c":"所","p":"suǒ"},{"c":"説","p":"shuō"},{"c":"的","p":"de"},{"c":"事","p":"shì"},{"c":"在","p":"zài"},{"c":"我","p":"wǒ"},{"c":"身上","p":"shēn shang"},{"c":"實現","p":"shí xiàn"},{"c":"。”"},{"c":"天使","p":"Tiān shǐ"},{"c":"就","p":"jiù"},{"c":"離開","p":"lí kāi"},{"c":"她","p":"tā"},{"c":"去","p":"qù"},{"c":"了","p":"le"},{"c":"。"}],[{"c":"39","v":39,"p":""},{"c":"在","p":"Zài"},{"c":"那","p":"nà"},{"c":"段","p":"duàn"},{"c":"日子","p":"rì zi"},{"c":"，"},{"c":"馬利亞","p":"Mǎ lì yà"},{"c":"起來","p":"qǐ lai"},{"c":"，"},{"c":"急忙","p":"jí máng"},{"c":"往","p":"wǎng"},{"c":"山地","p":"shān dì"},{"c":"去","p":"qù"},{"c":"，"},{"c":"來到","p":"lái dào"},{"c":"猶大","p":"Yóu dà"},{"c":"的","p":"de"},{"c":"一","p":"yí"},{"c":"座","p":"zuò"},{"c":"城","p":"chéng"},{"c":"。"},{"c":"40","v":40,"p":""},{"c":"她","p":"Tā"},{"c":"進了","p":"jìn le"},{"c":"撒迦利亞","p":"Sā jiā lì yà"},{"c":"的","p":"de"},{"c":"家","p":"jiā"},{"c":"，"},{"c":"向","p":"xiàng"},{"c":"伊利莎白","p":"Yī lì shā bái"},{"c":"問好","p":"wèn hǎo"},{"c":"。"},{"c":"41","v":41,"p":""},{"c":"不料","p":"Bú liào"},{"c":"伊利莎白","p":"Yī lì shā bái"},{"c":"一","p":"yì"},{"c":"聽到","p":"tīng dào"},{"c":"馬利亞","p":"Mǎ lì yà"},{"c":"的","p":"de"},{"c":"問候","p":"wèn hòu"},{"c":"，"},{"c":"腹","p":"fù"},{"c":"中","p":"zhōng"},{"c":"的","p":"de"},{"c":"胎兒","p":"tāi ’ér"},{"c":"就","p":"jiù"},{"c":"跳動","p":"tiào dòng"},{"c":"，"},{"c":"伊利莎白","p":"Yī lì shā bái"},{"c":"也","p":"yě"},{"c":"充滿","p":"chōng mǎn"},{"c":"聖靈","p":"shèng líng"},{"c":"，"},{"c":"42","v":42,"p":""},{"c":"大聲呼喊","p":"dà shēng hū hǎn"},{"c":"説","p":"shuō"},{"c":"："},{"c":"“","p":""},{"c":"你","p":"Nǐ"},{"c":"在","p":"zài"},{"c":"婦女","p":"fù nǚ"},{"c":"中","p":"zhōng"},{"c":"是","p":"shì"},{"c":"蒙福","p":"méng fú"},{"c":"的","p":"de"},{"c":"，"},{"c":"你","p":"nǐ"},{"c":"腹","p":"fù"},{"c":"中","p":"zhōng"},{"c":"的","p":"de"},{"c":"胎兒","p":"tāi ’ér"},{"c":"也","p":"yě"},{"c":"是","p":"shì"},{"c":"蒙福","p":"méng fú"},{"c":"的","p":"de"},{"c":"！"},{"c":"43","v":43,"p":""},{"c":"我","p":"Wǒ"},{"c":"主","p":"zhǔ"},{"c":"的","p":"de"},{"c":"母親","p":"mǔ qin"},{"c":"到","p":"dào"},{"c":"我","p":"wǒ"},{"c":"這裏","p":"zhè lǐ"},{"c":"來","p":"lái"},{"c":"，"},{"c":"我","p":"wǒ"},{"c":"多麼","p":"duō me"},{"c":"榮幸","p":"róng xìng"},{"c":"！"},{"c":"44","v":44,"p":""},{"c":"你","p":"Nǐ"},{"c":"看","p":"kàn"},{"c":"，"},{"c":"我","p":"wǒ"},{"c":"一","p":"yì"},{"c":"聽到","p":"tīng dào"},{"c":"你","p":"nǐ"},{"c":"問候","p":"wèn hòu"},{"c":"的","p":"de"},{"c":"聲音","p":"shēng yīn"},{"c":"，"},{"c":"我","p":"wǒ"},{"c":"腹","p":"fù"},{"c":"中","p":"zhōng"},{"c":"的","p":"de"},{"c":"嬰兒","p":"yīng ’ér"},{"c":"就","p":"jiù"},{"c":"歡喜","p":"huān xǐ"},{"c":"跳動","p":"tiào dòng"},{"c":"。"},{"c":"45","v":45,"p":""},{"c":"你","p":"Nǐ"},{"c":"既然","p":"jì rán"},{"c":"有","p":"yǒu"},{"c":"信心","p":"xìn xīn"},{"c":"，"},{"c":"也","p":"yě"},{"c":"就","p":"jiù"},{"c":"有福","p":"yǒu fú"},{"c":"了","p":"le"},{"c":"，"},{"c":"因為","p":"yīn wèi"},{"c":"耶和華","p":"Yē hé huá"},{"c":"告訴","p":"gào su"},{"c":"你","p":"nǐ"},{"c":"的","p":"de"},{"c":"事","p":"shì"},{"c":"，"},{"c":"必","p":"bì"},{"c":"完全","p":"wán quán"},{"c":"實現","p":"shí xiàn"},{"c":"。”"}],[{"c":"46","v":46,"p":""},{"c":"馬利亞","p":"Mǎ lì yà"},{"c":"説","p":"shuō"},{"c":"："},{"c":"“","p":""},{"c":"我","p":"Wǒ"},{"c":"衷心","p":"zhōng xīn"},{"c":"尊","p":"zūn"},{"c":"耶和華","p":"Yē hé huá"},{"c":"為","p":"wèi"},{"c":"大","p":"dà"},{"c":"，"},{"c":"47","v":47,"p":""},{"c":"我","p":"wǒ"},{"c":"心靈","p":"xīn líng"},{"c":"因","p":"yīn"},{"c":"上帝","p":"Shàng dì"},{"c":"我","p":"wǒ"},{"c":"的","p":"de"},{"c":"救主","p":"jiù zhǔ"},{"c":"非常","p":"fēi cháng"},{"c":"喜樂","p":"xǐ lè"},{"c":"，"},{"c":"48","v":48,"p":""},{"c":"因為","p":"yīn wèi"},{"c":"他","p":"tā"},{"c":"顧念","p":"gù niàn"},{"c":"他","p":"tā"},{"c":"婢女","p":"bì nǚ"},{"c":"的","p":"de"},{"c":"卑微","p":"bēi wēi"},{"c":"。"},{"c":"從今以後","p":"Cóng jīn yǐ hòu"},{"c":"，"},{"c":"萬代","p":"Wàn dài"},{"c":"必","p":"bì"},{"c":"説","p":"shuō"},{"c":"我","p":"wǒ"},{"c":"是","p":"shì"},{"c":"有福","p":"yǒu fú"},{"c":"的","p":"de"},{"c":"，"},{"c":"49","v":49,"p":""},{"c":"因為","p":"yīn wèi"},{"c":"大能者","p":"dà néng zhě"},{"c":"為","p":"wèi"},{"c":"我","p":"wǒ"},{"c":"行","p":"xíng"},{"c":"了","p":"le"},{"c":"大事","p":"dà shì"},{"c":"，"},{"c":"他","p":"tā"},{"c":"的","p":"de"},{"c":"名","p":"míng"},{"c":"是","p":"shì"},{"c":"神聖","p":"shén shèng"},{"c":"的","p":"de"},{"c":"。"},{"c":"50","v":50,"p":""},{"c":"他","p":"Tā"},{"c":"向","p":"xiàng"},{"c":"敬畏","p":"jìng wèi"},{"c":"他","p":"tā"},{"c":"的","p":"de"},{"c":"人","p":"rén"},{"c":"發","p":"fā"},{"c":"慈悲","p":"cí bēi"},{"c":"，"},{"c":"代代","p":"dài dài"},{"c":"無窮","p":"wú qióng"},{"c":"。"},{"c":"51","v":51,"p":""},{"c":"他","p":"Tā"},{"c":"用","p":"yòng"},{"c":"臂膀","p":"bì bǎng"},{"c":"施展","p":"shī zhǎn"},{"c":"大能","p":"dà néng"},{"c":"，"},{"c":"驅散","p":"qū sàn"},{"c":"心高氣傲","p":"xīn gāo –qì ’ào"},{"c":"的","p":"de"},{"c":"人","p":"rén"},{"c":"。"},{"c":"52","v":52,"p":""},{"c":"他","p":"Tā"},{"c":"使","p":"shǐ"},{"c":"掌權","p":"zhǎng quán"},{"c":"的","p":"de"},{"c":"失去","p":"shī qù"},{"c":"高位","p":"gāo wèi"},{"c":"，"},{"c":"卻","p":"què"},{"c":"叫","p":"jiào"},{"c":"卑微","p":"bēi wēi"},{"c":"的","p":"de"},{"c":"受到","p":"shòu dào"},{"c":"顯揚","p":"xiǎn yáng"},{"c":"；"},{"c":"53","v":53,"p":""},{"c":"他","p":"tā"},{"c":"用","p":"yòng"},{"c":"美物","p":"měi wù"},{"c":"使","p":"shǐ"},{"c":"飢餓","p":"jī ’è"},{"c":"的","p":"de"},{"c":"人","p":"rén"},{"c":"飽足","p":"bǎo zú"},{"c":"，"},{"c":"卻","p":"què"},{"c":"使","p":"shǐ"},{"c":"富有","p":"fù yǒu"},{"c":"的","p":"de"},{"c":"人","p":"rén"},{"c":"空手","p":"kōng shǒu"},{"c":"而","p":"ér"},{"c":"去","p":"qù"},{"c":"。"},{"c":"54","v":54,"p":""},{"c":"他","p":"Tā"},{"c":"來","p":"lái"},{"c":"扶助","p":"fú zhù"},{"c":"他","p":"tā"},{"c":"的","p":"de"},{"c":"僕人","p":"pú rén"},{"c":"以色列","p":"Yǐ sè liè"},{"c":"，"},{"c":"永不","p":"yǒng bú"},{"c":"忘記","p":"wàng jì"},{"c":"發","p":"fā"},{"c":"慈悲","p":"cí bēi"},{"c":"，"},{"c":"55","v":55,"p":""},{"c":"正如","p":"zhèng rú"},{"c":"他","p":"tā"},{"c":"對","p":"duì"},{"c":"我們","p":"wǒ men"},{"c":"祖先","p":"zǔ xiān"},{"c":"亞伯拉罕","p":"Yà bó lā hǎn"},{"c":"和","p":"hé"},{"c":"他","p":"tā"},{"c":"苗裔","p":"miáo yì"},{"c":"所","p":"suǒ"},{"c":"説","p":"shuō"},{"c":"的","p":"de"},{"c":"，"},{"c":"要","p":"yào"},{"c":"恩待","p":"ēn dài"},{"c":"他們","p":"tā men"},{"c":"。”"},{"c":"56","v":56,"p":""},{"c":"馬利亞","p":"Mǎ lì yà"},{"c":"就","p":"jiù"},{"c":"留","p":"liú"},{"c":"下來","p":"xià lai"},{"c":"，"},{"c":"在","p":"zài"},{"c":"那裏","p":"nà li"},{"c":"住了","p":"zhù le"},{"c":"約三","p":"Yuē –Sān"},{"c":"個","p":"ge"},{"c":"月","p":"yuè"},{"c":"才","p":"cái"},{"c":"回家","p":"huí jiā"},{"c":"去","p":"qù"},{"c":"。"}],[{"c":"57","v":57,"p":""},{"c":"伊利莎白","p":"Yī lì shā bái"},{"c":"的","p":"de"},{"c":"產期","p":"chǎn qī"},{"c":"到了","p":"dào le"},{"c":"，"},{"c":"就","p":"jiù"},{"c":"生了","p":"shēng le"},{"c":"一","p":"yí"},{"c":"個","p":"ge"},{"c":"兒子","p":"ér zi"},{"c":"。"},{"c":"58","v":58,"p":""},{"c":"鄰里","p":"Lín lǐ"},{"c":"親戚","p":"qīn qi"},{"c":"聽見","p":"tīng jiàn"},{"c":"耶和華","p":"Yē hé huá"},{"c":"向","p":"xiàng"},{"c":"她","p":"tā"},{"c":"大發","p":"dà fā"},{"c":"慈悲","p":"cí bēi"},{"c":"，"},{"c":"就","p":"jiù"},{"c":"跟","p":"gēn"},{"c":"她","p":"tā"},{"c":"一同","p":"yì tóng"},{"c":"歡樂","p":"huān lè"},{"c":"。"},{"c":"59","v":59,"p":""},{"c":"第八","p":"Dì –bā"},{"c":"天","p":"tiān"},{"c":"，"},{"c":"他們","p":"tā men"},{"c":"來","p":"lái"},{"c":"給","p":"gěi"},{"c":"孩子","p":"hái zi"},{"c":"行","p":"xíng"},{"c":"割禮","p":"gē lǐ"},{"c":"，"},{"c":"正","p":"zhèng"},{"c":"想","p":"xiǎng"},{"c":"照","p":"zhào"},{"c":"他","p":"tā"},{"c":"父親","p":"fù qin"},{"c":"的","p":"de"},{"c":"名字","p":"míng zi"},{"c":"叫","p":"jiào"},{"c":"他","p":"tā"},{"c":"撒迦利亞","p":"Sā jiā lì yà"},{"c":"，"},{"c":"60","v":60,"p":""},{"c":"他","p":"tā"},{"c":"母親","p":"mǔ qin"},{"c":"回答","p":"huí dá"},{"c":"説","p":"shuō"},{"c":"："},{"c":"“","p":""},{"c":"不","p":"Bù"},{"c":"！"},{"c":"他","p":"Tā"},{"c":"要","p":"yào"},{"c":"叫","p":"jiào"},{"c":"約翰","p":"Yuē hàn"},{"c":"。”"},{"c":"61","v":61,"p":""},{"c":"他們","p":"Tā men"},{"c":"對","p":"duì"},{"c":"伊利莎白","p":"Yī lì shā bái"},{"c":"説","p":"shuō"},{"c":"："},{"c":"“","p":""},{"c":"你","p":"Nǐ"},{"c":"親族","p":"qīn zú"},{"c":"當中","p":"dāng zhōng"},{"c":"沒有","p":"méi yǒu"},{"c":"人","p":"rén"},{"c":"叫","p":"jiào"},{"c":"這個","p":"zhè ge"},{"c":"名字","p":"míng zi"},{"c":"的","p":"de"},{"c":"。”"},{"c":"62","v":62,"p":""},{"c":"他們","p":"Tā men"},{"c":"就","p":"jiù"},{"c":"向","p":"xiàng"},{"c":"孩子","p":"hái zi"},{"c":"的","p":"de"},{"c":"父親","p":"fù qin"},{"c":"打","p":"dǎ"},{"c":"手勢","p":"shǒu shì"},{"c":"，"},{"c":"看","p":"kàn"},{"c":"他","p":"tā"},{"c":"要","p":"yào"},{"c":"給","p":"gěi"},{"c":"孩子","p":"hái zi"},{"c":"起","p":"qǐ"},{"c":"甚麼","p":"shén me"},{"c":"名字","p":"míng zi"},{"c":"。"},{"c":"63","v":63,"p":""},{"c":"撒迦利亞","p":"Sā jiā lì yà"},{"c":"要了","p":"yào le"},{"c":"塊","p":"kuài"},{"c":"字","p":"zì"},{"c":"板","p":"bǎn"},{"c":"，"},{"c":"寫下","p":"xiě xià"},{"c":"説","p":"shuō"},{"c":"："},{"c":"“","p":""},{"c":"他","p":"Tā"},{"c":"的","p":"de"},{"c":"名字","p":"míng zi"},{"c":"叫","p":"jiào"},{"c":"約翰","p":"Yuē hàn"},{"c":"。”"},{"c":"人人","p":"Rén rén"},{"c":"都","p":"dōu"},{"c":"驚奇","p":"jīng qí"},{"c":"不已","p":"bù yǐ"},{"c":"。"},{"c":"64","v":64,"p":""},{"c":"霎時間","p":"Shà shí jiān"},{"c":"，"},{"c":"撒迦利亞","p":"Sā jiā lì yà"},{"c":"的","p":"de"},{"c":"口","p":"kǒu"},{"c":"開","p":"kāi"},{"c":"了","p":"le"},{"c":"，"},{"c":"舌頭","p":"shé tou"},{"c":"解","p":"jiě"},{"c":"了","p":"le"},{"c":"，"},{"c":"就","p":"jiù"},{"c":"説出","p":"shuō chū"},{"c":"話","p":"huà"},{"c":"來","p":"lái"},{"c":"，"},{"c":"稱頌","p":"chēng sòng"},{"c":"上帝","p":"Shàng dì"},{"c":"。"},{"c":"65","v":65,"p":""},{"c":"鄰居","p":"Lín jū"},{"c":"全都","p":"quán dōu"},{"c":"起了","p":"qǐ le"},{"c":"敬畏","p":"jìng wèi"},{"c":"的","p":"de"},{"c":"心","p":"xīn"},{"c":"。"},{"c":"這","p":"Zhè"},{"c":"一切","p":"yí qiè"},{"c":"事","p":"shì"},{"c":"傳遍","p":"chuán biàn"},{"c":"全","p":"quán"},{"c":"猶地亞","p":"Yóu dì yà"},{"c":"山地","p":"shān dì"},{"c":"，"},{"c":"人人","p":"rén rén"},{"c":"談論","p":"tán lùn"},{"c":"。"},{"c":"66","v":66,"p":""},{"c":"凡","p":"Fán"},{"c":"聽見","p":"tīng jiàn"},{"c":"的","p":"de"},{"c":"都","p":"dōu"},{"c":"把","p":"bǎ"},{"c":"這些","p":"zhè xiē"},{"c":"事","p":"shì"},{"c":"記","p":"jì"},{"c":"在","p":"zài"},{"c":"心上","p":"xīn shang"},{"c":"，"},{"c":"説","p":"shuō"},{"c":"："},{"c":"“","p":""},{"c":"這個","p":"Zhè ge"},{"c":"孩子","p":"hái zi"},{"c":"將來","p":"jiāng lái"},{"c":"怎樣","p":"zěn yàng"},{"c":"呢","p":"ne"},{"c":"？”"},{"c":"耶和華","p":"Yē hé huá"},{"c":"的","p":"de"},{"c":"手","p":"shǒu"},{"c":"確實","p":"què shí"},{"c":"與","p":"yǔ"},{"c":"他","p":"tā"},{"c":"同在","p":"tóng zài"},{"c":"。"}],[{"c":"67","v":67,"p":""},{"c":"孩子","p":"Hái zi"},{"c":"的","p":"de"},{"c":"父親","p":"fù qin"},{"c":"撒迦利亞","p":"Sā jiā lì yà"},{"c":"充滿","p":"chōng mǎn"},{"c":"聖靈","p":"shèng líng"},{"c":"，"},{"c":"預言","p":"yù yán"},{"c":"説","p":"shuō"},{"c":"："},{"c":"68","v":68,"p":""},{"c":"“","p":""},{"c":"願","p":"yuàn"},{"c":"稱頌","p":"chēng sòng"},{"c":"歸於","p":"guī yú"},{"c":"以色列","p":"Yǐ sè liè"},{"c":"的","p":"de"},{"c":"上帝","p":"Shàng dì"},{"c":"耶和華","p":"Yē hé huá"},{"c":"，"},{"c":"因為","p":"yīn wèi"},{"c":"他","p":"tā"},{"c":"顧念","p":"gù niàn"},{"c":"他","p":"tā"},{"c":"的","p":"de"},{"c":"子民","p":"zǐ mín"},{"c":"，"},{"c":"搭救","p":"dā jiù"},{"c":"他們","p":"tā men"},{"c":"，"},{"c":"69","v":69,"p":""},{"c":"在","p":"zài"},{"c":"他","p":"tā"},{"c":"僕人","p":"pú rén"},{"c":"大衛","p":"Dà wèi"},{"c":"的","p":"de"},{"c":"家","p":"jiā"},{"c":"裏","p":"lǐ"},{"c":"，"},{"c":"給","p":"gěi"},{"c":"我們","p":"wǒ men"},{"c":"興起了","p":"xīng qǐ le"},{"c":"拯救","p":"zhěng jiù"},{"c":"的","p":"de"},{"c":"角","p":"jiǎo"},{"c":"，"},{"c":"70","v":70,"p":""},{"c":"正如","p":"zhèng rú"},{"c":"他","p":"tā"},{"c":"自古以來","p":"zì gǔ yǐ lái"},{"c":"通過","p":"tōng guò"},{"c":"聖","p":"shèng"},{"c":"先知","p":"xiān zhī"},{"c":"的","p":"de"},{"c":"口","p":"kǒu"},{"c":"所","p":"suǒ"},{"c":"説","p":"shuō"},{"c":"的","p":"de"},{"c":"。"},{"c":"71","v":71,"p":""},{"c":"他","p":"Tā"},{"c":"應許","p":"yīng xǔ"},{"c":"救","p":"jiù"},{"c":"我們","p":"wǒ men"},{"c":"脫離","p":"tuō lí"},{"c":"仇敵","p":"chóu dí"},{"c":"，"},{"c":"擺脫","p":"bǎi tuō"},{"c":"所有","p":"suǒ yǒu"},{"c":"憎恨","p":"zēng hèn"},{"c":"我們","p":"wǒ men"},{"c":"的","p":"de"},{"c":"人","p":"rén"},{"c":"的","p":"de"},{"c":"手","p":"shǒu"},{"c":"，"},{"c":"72","v":72,"p":""},{"c":"為了","p":"wèi le"},{"c":"我們","p":"wǒ men"},{"c":"的","p":"de"},{"c":"列祖","p":"liè zǔ"},{"c":"大發","p":"dà fā"},{"c":"慈悲","p":"cí bēi"},{"c":"，"},{"c":"沒有","p":"méi yǒu"},{"c":"忘記","p":"wàng jì"},{"c":"他","p":"tā"},{"c":"的","p":"de"},{"c":"聖約","p":"shèng yuē"},{"c":"，"},{"c":"73","v":73,"p":""},{"c":"就是","p":"jiù shì"},{"c":"他","p":"tā"},{"c":"向","p":"xiàng"},{"c":"我們","p":"wǒ men"},{"c":"祖先","p":"zǔ xiān"},{"c":"亞伯拉罕","p":"Yà bó lā hǎn"},{"c":"所","p":"suǒ"},{"c":"發","p":"fā"},{"c":"的","p":"de"},{"c":"誓","p":"shì"},{"c":"。"},{"c":"74","v":74,"p":""},{"c":"他","p":"Tā"},{"c":"把","p":"bǎ"},{"c":"我們","p":"wǒ men"},{"c":"從","p":"cóng"},{"c":"仇敵","p":"chóu dí"},{"c":"手","p":"shǒu"},{"c":"裏","p":"lǐ"},{"c":"救了","p":"jiù le"},{"c":"出來","p":"chū lái"},{"c":"，"},{"c":"就","p":"jiù"},{"c":"讓","p":"ràng"},{"c":"我們","p":"wǒ men"},{"c":"有幸","p":"yǒu xìng"},{"c":"坦然","p":"tǎn rán"},{"c":"敬奉","p":"jìng fèng"},{"c":"他","p":"tā"},{"c":"，"},{"c":"75","v":75,"p":""},{"c":"一生","p":"yì shēng"},{"c":"在","p":"zài"},{"c":"他","p":"tā"},{"c":"面前","p":"miàn qián"},{"c":"盡忠","p":"jìn zhōng"},{"c":"行義","p":"xíng yì"},{"c":"。"},{"c":"76","v":76,"p":""},{"c":"孩子","p":"Hái zi"},{"c":"啊","p":"a"},{"c":"，"},{"c":"你","p":"nǐ"},{"c":"必","p":"bì"},{"c":"稱","p":"chēng"},{"c":"為","p":"wéi"},{"c":"至高者","p":"zhì gāo zhě"},{"c":"的","p":"de"},{"c":"先知","p":"xiān zhī"},{"c":"。"},{"c":"你","p":"Nǐ"},{"c":"必","p":"bì"},{"c":"在","p":"zài"},{"c":"耶和華","p":"Yē hé huá"},{"c":"前面","p":"qián mian"},{"c":"先行","p":"xiān xíng"},{"c":"，"},{"c":"為","p":"wèi"},{"c":"他","p":"tā"},{"c":"預備","p":"yù bèi"},{"c":"道路","p":"dào lù"},{"c":"，"},{"c":"77","v":77,"p":""},{"c":"使","p":"shǐ"},{"c":"他","p":"tā"},{"c":"子民","p":"zǐ mín"},{"c":"的","p":"de"},{"c":"罪","p":"zuì"},{"c":"得","p":"dé"},{"c":"蒙","p":"méng"},{"c":"寬恕","p":"kuān shù"},{"c":"，"},{"c":"他們","p":"tā men"},{"c":"就","p":"jiù"},{"c":"認識","p":"rèn shi"},{"c":"救恩","p":"jiù ’ēn"},{"c":"。"},{"c":"78","v":78,"p":""},{"c":"我們","p":"Wǒ men"},{"c":"的","p":"de"},{"c":"上帝","p":"Shàng dì"},{"c":"實在","p":"shí zài"},{"c":"有","p":"yǒu"},{"c":"親切","p":"qīn qiè"},{"c":"憐恤","p":"lián xù"},{"c":"的","p":"de"},{"c":"心","p":"xīn"},{"c":"。"},{"c":"因此","p":"Yīn cǐ"},{"c":"曙光","p":"shǔ guāng"},{"c":"必","p":"bì"},{"c":"從","p":"cóng"},{"c":"高天","p":"gāo tiān"},{"c":"臨到","p":"lín dào"},{"c":"我們","p":"wǒ men"},{"c":"，"},{"c":"79","v":79,"p":""},{"c":"照耀","p":"zhào yào"},{"c":"坐","p":"zuò"},{"c":"在","p":"zài"},{"c":"黑暗","p":"hēi ’àn"},{"c":"和","p":"hé"},{"c":"死","p":"sǐ"},{"c":"蔭","p":"yìn"},{"c":"的","p":"de"},{"c":"人","p":"rén"},{"c":"，"},{"c":"指引","p":"zhǐ yǐn"},{"c":"我們","p":"wǒ men"},{"c":"的","p":"de"},{"c":"腳步","p":"jiǎo bù"},{"c":"，"},{"c":"順順利利","p":"shùn shùn lì lì"},{"c":"地","p":"de"},{"c":"行走","p":"xíng zǒu"},{"c":"平安","p":"píng ’ān"},{"c":"之","p":"zhī"},{"c":"路","p":"lù"},{"c":"。”"}],[{"c":"80","v":80,"p":""},{"c":"孩子","p":"Hái zi"},{"c":"漸漸","p":"jiàn jiàn"},{"c":"長大","p":"zhǎng dà"},{"c":"，"},{"c":"心靈","p":"xīn líng"},{"c":"強健","p":"qiáng jiàn"},{"c":"。"},{"c":"他","p":"Tā"},{"c":"住","p":"zhù"},{"c":"在","p":"zài"},{"c":"荒山野嶺","p":"huāng shān yě lǐng"},{"c":"，"},{"c":"直到","p":"zhí dào"},{"c":"向","p":"xiàng"},{"c":"以色列人","p":"Yǐ sè liè rén"},{"c":"公開","p":"gōng kāi"},{"c":"露面","p":"lòu miàn"},{"c":"的","p":"de"},{"c":"日子","p":"rì zi"},{"c":"。"}]]}